sqls/interfaces/__init__.py
sqls/interfaces/py.typed
sqls/models/__init__.py
sqls/models/fields.py
sqls/models/generators.py
sqls/models/model.py
sqls/models/py.typed
sqls/queries/__init__.py
sqls/queries/alter.py
sqls/queries/analyze.py
sqls/queries/attach.py
sqls/queries/base.py
sqls/queries/create_index.py
sqls/queries/create_table.py
sqls/queries/create_trigger.py
sqls/queries/create_view.py
sqls/queries/delete.py
sqls/queries/detach.py
sqls/queries/drop.py
sqls/queries/exceptions.py
sqls/queries/explain.py
sqls/queries/expr.py
sqls/queries/insert.py
sqls/queries/pragma.py
sqls/queries/py.typed
sqls/queries/query.py
sqls/queries/reindex.py
sqls/queries/select.py
sqls/queries/table.py
sqls/queries/update.py
sqls/queries/vacuum.py
sqls/queries/window.py
sqls/queries/withq.py
sqls/transactions/__init__.py
sqls/transactions/exceptions.py
sqls/transactions/manager.py
sqls/transactions/mysql.py
sqls/transactions/postgresql.py
sqls/transactions/py.typed
sqls/transactions/sqlite.py
sqls-0.0.103.dist-info/licenses/LICENSE.txt
sqls-0.0.103.dist-info/METADATA
sqls-0.0.103.dist-info/WHEEL
sqls-0.0.103.dist-info/top_level.txt
sqls-0.0.103.dist-info/RECORD
