Metadata-Version: 2.4
Name: sqls
Version: 0.0.103
Summary: SQL Toolkit for Python.
Author-email: Marko Durkovic <marko@miding.de>
License-Expression: Apache-2.0
Project-URL: Homepage, https://gitlab.com/durko/sqls
Project-URL: Documentation, https://durko.gitlab.io/sqls
Project-URL: Source, https://gitlab.com/durko/sqls
Project-URL: Issues, https://gitlab.com/durko/sqls/issues
Project-URL: Changelog, https://gitlab.com/durko/sqls/-/blob/master/CHANGES.rst
Keywords: aio,async,database,mariadb,model,mysql,query,postgresql,sql,sqlite3,transaction
Classifier: Development Status :: 4 - Beta
Classifier: Programming Language :: Python
Classifier: Programming Language :: Python :: 3 :: Only
Classifier: Programming Language :: Python :: 3.10
Classifier: Programming Language :: Python :: 3.11
Classifier: Programming Language :: Python :: 3.12
Classifier: Programming Language :: Python :: 3.13
Classifier: Programming Language :: Python :: 3.14
Classifier: Topic :: Database
Classifier: Typing :: Typed
Requires-Python: >=3.10
License-File: LICENSE.txt
Provides-Extra: mysql
Requires-Dist: aiomysql; extra == "mysql"
Provides-Extra: postgresql
Requires-Dist: asyncpg; extra == "postgresql"
Provides-Extra: sqlite
Requires-Dist: aiosqlite; extra == "sqlite"
Dynamic: license-file
